jls_utils/__init__.py
jls_utils/utils.py
jls_utils/abstract/__init__.py
jls_utils/abstract/abstract.py
jls_utils/funcs/__init__.py
jls_utils/funcs/funcs.py
jls_utils/funcs/helpers.py
jls_utils/secondary/__init__.py
jls_utils/secondary/config.py
jls_utils/secondary/const.py
jls_utils/secondary/helpers.py
jls_utils-0.1.37.dist-info/METADATA
jls_utils-0.1.37.dist-info/WHEEL
jls_utils-0.1.37.dist-info/top_level.txt
jls_utils-0.1.37.dist-info/RECORD
