Metadata-Version: 2.1
Name: jls-utils
Version: 0.1.37
Author: Andrew Pogrebnoj
Author-email: andrew2000203@gmail.com
Requires-Dist: requests
Requires-Dist: pydantic
Requires-Dist: typing
Requires-Dist: pandas
Requires-Dist: deprecation
Requires-Dist: aiohttp
